librelingo_fakes-3.2.1.dist-info/METADATA
librelingo_fakes-3.2.1.dist-info/WHEEL
librelingo_fakes/__init__.py
librelingo_fakes/fakes.py
librelingo_fakes-3.2.1.dist-info/RECORD
