Metadata-Version: 2.1
Name: librelingo_fakes
Version: 3.2.1
Summary: Fake data for testing LibreLingo-related packages
Author-Email: =?utf-8?b?RMOhbmllbCBLw6FudG9y?= <git@daniel-kantor.com>
License: GPLv3
Requires-Python: >=3.11
Requires-Dist: librelingo-types>=3.3.0
